yt_dlp_plugins/extractor/yt_jsc_youtubei.py
yt_jsc_youtubei-0.0.1.dist-info/METADATA
yt_jsc_youtubei-0.0.1.dist-info/WHEEL
yt_jsc_youtubei-0.0.1.dist-info/licenses/LICENSE.txt
yt_jsc_youtubei-0.0.1.dist-info/RECORD
