Metadata-Version: 2.4
Name: yt-jsc-youtubei
Version: 0.0.1
Summary: Js Challenge Provider based on youtubei.js
License-Expression: MIT
License-File: LICENSE.txt
Keywords: yt-dlp,yt-dlp-jsc-provider
Author: alive4ever
Author-email: alive4ever@users.noreply.github.com
Requires-Python: >=3.10
Classifier: Programming Language :: Python :: 3
Classifier: Programming Language :: Python :: 3.10
Classifier: Programming Language :: Python :: 3.11
Classifier: Programming Language :: Python :: 3.12
Classifier: Programming Language :: Python :: 3.13
Classifier: Programming Language :: Python :: 3.14
Requires-Dist: yt-dlp (>=2025.11.12)
Project-URL: Bug tracker, https://github.com/alive4ever/yt-jsc-youtubei/issues
Project-URL: Documentation, https://github.com/alive4ever/yt-jsc-youtubei
Project-URL: Homepage, https://github.com/alive4ever/yt-jsc-youtubei
Project-URL: Repository, https://github.com/alive4ever/yt-jsc-youtubei
